quickmacapp/__init__.py
quickmacapp/_background.py
quickmacapp/_interactions.py
quickmacapp/_notifications.py
quickmacapp/_quickapp.py
quickmacapp/notifications.py
quickmacapp/py.typed
quickmacapp-2025.7.22.dist-info/licenses/LICENSE
quickmacapp-2025.7.22.dist-info/METADATA
quickmacapp-2025.7.22.dist-info/WHEEL
quickmacapp-2025.7.22.dist-info/top_level.txt
quickmacapp-2025.7.22.dist-info/RECORD
