Metadata-Version: 2.4
Name: quickmacapp
Version: 2025.7.22
Summary: Make it easier to write Mac apps in Python
License-File: LICENSE
Requires-Dist: pyobjc-framework-Cocoa
Requires-Dist: pyobjc-framework-ExceptionHandling
Requires-Dist: pyobjc-framework-UserNotifications
Requires-Dist: datetype
Requires-Dist: twisted[macos_platform,tls]
Dynamic: license-file
